ovos_media_plugin_simple/__init__.py
ovos_media_plugin_simple/version.py
ovos_media_plugin_simple-0.0.2a5.dist-info/LICENSE
ovos_media_plugin_simple-0.0.2a5.dist-info/METADATA
ovos_media_plugin_simple-0.0.2a5.dist-info/WHEEL
ovos_media_plugin_simple-0.0.2a5.dist-info/entry_points.txt
ovos_media_plugin_simple-0.0.2a5.dist-info/top_level.txt
ovos_media_plugin_simple-0.0.2a5.dist-info/RECORD
