Metadata-Version: 2.1
Name: ovos-media-plugin-simple
Version: 0.0.2a5
Summary: simple OCP plugin for ovos
Home-page: https://github.com/OpenVoiceOS/ovos-media-plugin-simple
Author: JarbasAi
Author-email: jarbasai@mailfence.com
License: Apache-2.0
Keywords: ovos audio OCP plugin
Platform: UNKNOWN
Requires-Dist: ovos-plugin-manager >=0.0.26a5
